reasoning_machine/__init__.py
reasoning_machine-0.0.2.dist-info/LICENSE
reasoning_machine-0.0.2.dist-info/METADATA
reasoning_machine-0.0.2.dist-info/WHEEL
reasoning_machine-0.0.2.dist-info/top_level.txt
reasoning_machine-0.0.2.dist-info/RECORD
