Metadata-Version: 2.1
Name: reasoning-machine
Version: 0.0.2
Summary: Reasoning Machine
Author-email: Alexander Fedotov <alex.fedotov@aol.com>
Project-URL: Homepage, https://github.com/reasoning-machine/reasoning-machine
Project-URL: Bug Tracker, https://github.com/reasoning-machine/reasoning-machine/issues
Classifier: Programming Language :: Python :: 3
Classifier: License :: OSI Approved :: MIT License
Classifier: Operating System :: OS Independent
Requires-Python: >=3.10
License-File: LICENSE
